{
  "day": "20251125",
  "total": 30,
  "questions": [
    {
      "Title": "NSCA CSCS 問題集 (61/90)",
      "Date": "2025年11月25日",
      "Field": "リハビリテーションと再調整",
      "Theme": "急性期対応",
      "Level": "Level 1",
      "QuizType": "",
      "Number": 1,
      "Question": "急性期の​RICE​処置に含まれない要素はどれか？",
      "Option_A": "Ice",
      "Option_B": "Compression",
      "Option_C": "Elevation",
      "Option_D": "Heat",
      "Correct": "A",
      "Explanation": "RICEはRest, Ice, Compression, Elevationの略。急性期は安静・冷却・圧迫・挙上を用いる。温熱（Heat）は炎症拡大の恐れがあり含まれない。",
      "Tag_Cause": "炎症抑制|冷却管理",
      "Tag_Process": "安静|圧迫挙上",
      "Tag_Outcome": "腫脹抑制|疼痛軽減"
    },
    {
      "Title": "NSCA CSCS 問題集 (61/90)",
      "Date": "2025年11月25日",
      "Field": "リハビリテーションと再調整",
      "Theme": "炎症期対応",
      "Level": "Level 1",
      "QuizType": "",
      "Number": 2,
      "Question": "損傷直後のアイシングの主目的はどれか？",
      "Option_A": "代謝促進",
      "Option_B": "炎症拡大の抑制",
      "Option_C": "筋肥大促進",
      "Option_D": "柔軟性向上",
      "Correct": "A",
      "Explanation": "アイシングは局所血流と代謝を抑え、炎症の広がりと浮腫形成を抑制する。疼痛軽減にも寄与する。",
      "Tag_Cause": "冷却介入|血流制限",
      "Tag_Process": "代謝抑制|炎症抑制",
      "Tag_Outcome": "浮腫軽減|疼痛緩和"
    },
    {
      "Title": "NSCA CSCS 問題集 (61/90)",
      "Date": "2025年11月25日",
      "Field": "リハビリテーションと再調整",
      "Theme": "可動域改善",
      "Level": "Level 1",
      "QuizType": "",
      "Number": 3,
      "Question": "初期リハで“痛みを我慢して可動域拡大”を行うリスクはどれか？",
      "Option_A": "筋力低下",
      "Option_B": "呼吸数低下",
      "Option_C": "再炎症と瘢痕悪化",
      "Option_D": "血圧上昇",
      "Correct": "A",
      "Explanation": "疼痛下での強行は組織損傷と炎症再燃を起こす。無痛域でのROM訓練が安全かつ有効。",
      "Tag_Cause": "疼痛下過負荷",
      "Tag_Process": "組織損傷|炎症再燃",
      "Tag_Outcome": "ROM維持|安全回復"
    },
    {
      "Title": "NSCA CSCS 問題集 (61/90)",
      "Date": "2025年11月25日",
      "Field": "リハビリテーションと再調整",
      "Theme": "急性期対応",
      "Level": "Level 1",
      "QuizType": "",
      "Number": 4,
      "Question": "固定期間中に重点を置くべき介入はどれか？",
      "Option_A": "全身の血流維持運動",
      "Option_B": "患部筋の高強度トレ",
      "Option_C": "完全安静のみ継続",
      "Option_D": "無呼吸訓練",
      "Correct": "A",
      "Explanation": "固定部位以外の運動や呼吸訓練により全身循環を保ち、治癒環境を整える。",
      "Tag_Cause": "固定安静期",
      "Tag_Process": "非患部運動|呼吸訓練",
      "Tag_Outcome": "循環維持|治癒促進"
    },
    {
      "Title": "NSCA CSCS 問題集 (61/90)",
      "Date": "2025年11月25日",
      "Field": "リハビリテーションと再調整",
      "Theme": "炎症期対応",
      "Level": "Level 1",
      "QuizType": "",
      "Number": 5,
      "Question": "炎症期に避けるべき刺激はどれか？",
      "Option_A": "軽い可動域維持",
      "Option_B": "他動ROM",
      "Option_C": "患部挙上",
      "Option_D": "強い摩擦や深部加温",
      "Correct": "A",
      "Explanation": "炎症初期に深部加温や強摩擦は血流増加で炎症を助長する。冷却と軽動作維持が基本。",
      "Tag_Cause": "炎症初期|血流過多",
      "Tag_Process": "深部加温回避|冷却維持",
      "Tag_Outcome": "炎症抑制|疼痛緩和"
    },
    {
      "Title": "NSCA CSCS 問題集 (61/90)",
      "Date": "2025年11月25日",
      "Field": "リハビリテーションと再調整",
      "Theme": "筋力回復",
      "Level": "Level 1",
      "QuizType": "",
      "Number": 6,
      "Question": "筋萎縮予防に早期から導入しやすいのはどれか？",
      "Option_A": "エキセントリック",
      "Option_B": "等尺性収縮",
      "Option_C": "プライオメトリクス",
      "Option_D": "高速度トレーニング",
      "Correct": "A",
      "Explanation": "等尺性収縮は関節動作を伴わず筋活動を維持できる。痛みのない範囲で筋萎縮防止に有効。",
      "Tag_Cause": "関節安静|疼痛回避",
      "Tag_Process": "等尺性収縮導入",
      "Tag_Outcome": "筋活動維持|萎縮防止"
    },
    {
      "Title": "NSCA CSCS 問題集 (61/90)",
      "Date": "2025年11月25日",
      "Field": "リハビリテーションと再調整",
      "Theme": "疼痛管理",
      "Level": "Level 1",
      "QuizType": "",
      "Number": 7,
      "Question": "疼痛管理の補助手段として妥当なのはどれか？",
      "Option_A": "アイシングと軽運動",
      "Option_B": "温熱と強圧マッサージ",
      "Option_C": "最大挙上運動",
      "Option_D": "完全固定のみ",
      "Correct": "A",
      "Explanation": "冷却により神経伝達速度が低下し痛みを緩和。軽運動で血流を維持する。",
      "Tag_Cause": "冷却|軽運動",
      "Tag_Process": "神経伝導抑制|血流維持",
      "Tag_Outcome": "疼痛軽減|代謝安定"
    },
    {
      "Title": "NSCA CSCS 問題集 (61/90)",
      "Date": "2025年11月25日",
      "Field": "リハビリテーションと再調整",
      "Theme": "動作再学習",
      "Level": "Level 1",
      "QuizType": "",
      "Number": 8,
      "Question": "早期荷重許可後に優先される課題はどれか？",
      "Option_A": "高跳び訓練",
      "Option_B": "最大ダッシュ",
      "Option_C": "歩行パターンと荷重分配の再学習",
      "Option_D": "全力筋力測定",
      "Correct": "A",
      "Explanation": "不良歩行パターンが再発リスクとなるため，正しい荷重と歩行動作の再教育を行う。",
      "Tag_Cause": "早期荷重許可",
      "Tag_Process": "歩行動作再教育",
      "Tag_Outcome": "荷重安定|再発防止"
    },
    {
      "Title": "NSCA CSCS 問題集 (61/90)",
      "Date": "2025年11月25日",
      "Field": "リハビリテーションと再調整",
      "Theme": "神経筋再教育",
      "Level": "Level 1",
      "QuizType": "",
      "Number": 9,
      "Question": "患部以外の部位を鍛える“クロスエデュケーション”の効果はどれか？",
      "Option_A": "患部側への神経促通",
      "Option_B": "反対側筋の廃用促進",
      "Option_C": "循環抑制",
      "Option_D": "疼痛増悪",
      "Correct": "A",
      "Explanation": "非損傷側のトレーニングにより中枢神経経路が刺激され、患側筋にも活動促通が起きる。",
      "Tag_Cause": "非患側訓練",
      "Tag_Process": "中枢経路活性化",
      "Tag_Outcome": "患側筋活動促通|回復促進"
    },
    {
      "Title": "NSCA CSCS 問題集 (61/90)",
      "Date": "2025年11月25日",
      "Field": "リハビリテーションと再調整",
      "Theme": "可動域改善",
      "Level": "Level 1",
      "QuizType": "",
      "Number": 10,
      "Question": "呼吸訓練の目的として最も適切なのはどれか？",
      "Option_A": "呼吸筋疲労の固定化",
      "Option_B": "代謝抑制",
      "Option_C": "酸素摂取抑制",
      "Option_D": "胸郭可動性維持と循環促進",
      "Correct": "A",
      "Explanation": "胸郭の可動性を保ち、酸素供給と血流循環を支える。固定期にも全身機能を維持する。",
      "Tag_Cause": "呼吸訓練実施",
      "Tag_Process": "胸郭可動性維持",
      "Tag_Outcome": "酸素供給|循環改善"
    },
    {
      "Title": "NSCA CSCS 問題集 (61/90)",
      "Date": "2025年11月25日",
      "Field": "リハビリテーションと再調整",
      "Theme": "エキセントリック訓練",
      "Level": "Level 2",
      "QuizType": "",
      "Number": 11,
      "Question": "慢性腱障害の管理で中心となる運動様式はどれか？",
      "Option_A": "等尺性のみ",
      "Option_B": "等張性短縮のみ",
      "Option_C": "エキセントリック収縮",
      "Option_D": "静止安静",
      "Correct": "A",
      "Explanation": "慢性期ではエキセントリック負荷が腱線維の再配向と強度改善を促す。痛みの範囲で実施する。",
      "Tag_Cause": "腱線維損傷",
      "Tag_Process": "エキセントリック負荷導入",
      "Tag_Outcome": "線維再配向|強度改善"
    },
    {
      "Title": "NSCA CSCS 問題集 (61/90)",
      "Date": "2025年11月25日",
      "Field": "リハビリテーションと再調整",
      "Theme": "姿勢制御再建",
      "Level": "Level 2",
      "QuizType": "",
      "Number": 12,
      "Question": "腰部痛で体幹安定性を高める目的に最も有効な初期介入はどれか？",
      "Option_A": "高速度回旋",
      "Option_B": "ブレーシングとニュートラル維持",
      "Option_C": "深屈曲ストレッチ",
      "Option_D": "最大重量リフト",
      "Correct": "A",
      "Explanation": "腰部安定化には腹横筋などの深層筋を活性化しニュートラル保持を学習することが基本となる。",
      "Tag_Cause": "体幹不安定|腰痛",
      "Tag_Process": "深層筋活性|ニュートラル保持",
      "Tag_Outcome": "姿勢安定|疼痛軽減"
    },
    {
      "Title": "NSCA CSCS 問題集 (61/90)",
      "Date": "2025年11月25日",
      "Field": "リハビリテーションと再調整",
      "Theme": "神経筋再教育",
      "Level": "Level 2",
      "QuizType": "",
      "Number": 13,
      "Question": "肩インピンジメントで重点を置くべき筋群はどれか？",
      "Option_A": "三角筋前部のみ",
      "Option_B": "上腕二頭筋長頭",
      "Option_C": "肩甲下筋と下方回旋筋群",
      "Option_D": "下方回旋筋群の抑制と上方回旋筋群の協調",
      "Correct": "A",
      "Explanation": "肩甲骨上方回旋に関与する前鋸筋・下部僧帽筋の活性化が重要。肩峰下スペースを保つ。",
      "Tag_Cause": "肩峰下圧迫|肩甲帯不均衡",
      "Tag_Process": "前鋸筋|下部僧帽筋活性",
      "Tag_Outcome": "肩峰下スペース確保|疼痛抑制"
    },
    {
      "Title": "NSCA CSCS 問題集 (61/90)",
      "Date": "2025年11月25日",
      "Field": "リハビリテーションと再調整",
      "Theme": "荷重進行",
      "Level": "Level 2",
      "QuizType": "",
      "Number": 14,
      "Question": "膝関節術後の開放性運動導入で注意すべきはどれか？",
      "Option_A": "ROM維持効果",
      "Option_B": "筋萎縮抑制",
      "Option_C": "循環改善",
      "Option_D": "遠位負荷によるせん断力増加",
      "Correct": "A",
      "Explanation": "遠位での負荷は関節にせん断力を与え再建組織を刺激する。治癒段階を考慮して導入する。",
      "Tag_Cause": "膝術後組織脆弱",
      "Tag_Process": "せん断力評価|OKC管理",
      "Tag_Outcome": "再建組織保護|安全導入"
    },
    {
      "Title": "NSCA CSCS 問題集 (61/90)",
      "Date": "2025年11月25日",
      "Field": "リハビリテーションと再調整",
      "Theme": "神経筋再教育",
      "Level": "Level 2",
      "QuizType": "",
      "Number": 15,
      "Question": "筋出力回復のために活用できる神経促通法はどれか？",
      "Option_A": "PNF（固有受容性神経筋促通）",
      "Option_B": "ストレッチのみ",
      "Option_C": "完全固定",
      "Option_D": "等張性短縮のみ",
      "Correct": "A",
      "Explanation": "PNFは感覚入力を用いて神経筋協調を高める。姿勢・抵抗方向を変化させることで再教育に効果的。",
      "Tag_Cause": "神経筋協調低下",
      "Tag_Process": "PNF導入|感覚入力促通",
      "Tag_Outcome": "出力回復|動作再教育"
    },
    {
      "Title": "NSCA CSCS 問題集 (61/90)",
      "Date": "2025年11月25日",
      "Field": "リハビリテーションと再調整",
      "Theme": "再受傷予防",
      "Level": "Level 3",
      "QuizType": "",
      "Number": 16,
      "Question": "片脚着地動作で確認すべきリスク因子はどれか？",
      "Option_A": "膝外反ゼロのみ",
      "Option_B": "心拍変動",
      "Option_C": "膝内反・体幹傾斜",
      "Option_D": "呼吸数",
      "Correct": "A",
      "Explanation": "膝内反や体幹の傾斜は再受傷リスクを高める。動作制御の指標として評価する。",
      "Tag_Cause": "着地動作評価",
      "Tag_Process": "膝内反|体幹傾斜分析",
      "Tag_Outcome": "動作修正|再受傷防止"
    },
    {
      "Title": "NSCA CSCS 問題集 (61/90)",
      "Date": "2025年11月25日",
      "Field": "リハビリテーションと再調整",
      "Theme": "段階的復帰設計",
      "Level": "Level 3",
      "QuizType": "",
      "Number": 17,
      "Question": "プライオ導入期の適切な接地管理はどれか？",
      "Option_A": "高頻度で無制限反復",
      "Option_B": "接地数と強度を段階的に増やす",
      "Option_C": "休息なしで連続化",
      "Option_D": "痛み無視で強行",
      "Correct": "A",
      "Explanation": "プライオでは接地数と強度を管理し，漸進的に適応を高めることが安全である。",
      "Tag_Cause": "接地負荷増大",
      "Tag_Process": "接地数管理|強度漸増",
      "Tag_Outcome": "適応促進|安全進行"
    },
    {
      "Title": "NSCA CSCS 問題集 (61/90)",
      "Date": "2025年11月25日",
      "Field": "リハビリテーションと再調整",
      "Theme": "復帰基準",
      "Level": "Level 3",
      "QuizType": "",
      "Number": 18,
      "Question": "走行復帰前に確認すべき要素はどれか？",
      "Option_A": "最大挙上重量",
      "Option_B": "心拍最大値",
      "Option_C": "疼痛閾値と腫脹反応",
      "Option_D": "VO2max",
      "Correct": "A",
      "Explanation": "痛みや腫脹が悪化しない範囲で漸進する必要がある。症状モニタリングが鍵となる。",
      "Tag_Cause": "疼痛|腫脹評価",
      "Tag_Process": "症状モニタリング",
      "Tag_Outcome": "安全復帰|悪化防止"
    },
    {
      "Title": "NSCA CSCS 問題集 (61/90)",
      "Date": "2025年11月25日",
      "Field": "リハビリテーションと再調整",
      "Theme": "再発予防",
      "Level": "Level 3",
      "QuizType": "",
      "Number": 19,
      "Question": "スポーツ動作復帰期に重要な心理的因子はどれか？",
      "Option_A": "恐怖回避と自己効力感",
      "Option_B": "緊張の放置",
      "Option_C": "身体意識の否定",
      "Option_D": "痛みの無視",
      "Correct": "A",
      "Explanation": "恐怖回避行動の克服と自己効力感の回復が復帰意欲と動作品質を高める。",
      "Tag_Cause": "恐怖回避|自信低下",
      "Tag_Process": "心理教育|自己効力感回復",
      "Tag_Outcome": "動作品質向上|復帰促進"
    },
    {
      "Title": "NSCA CSCS 問題集 (61/90)",
      "Date": "2025年11月25日",
      "Field": "リハビリテーションと再調整",
      "Theme": "再発予防",
      "Level": "Level 3",
      "QuizType": "",
      "Number": 20,
      "Question": "慢性腰痛における“再発予防”で有効な運動要素はどれか？",
      "Option_A": "筋力のみ追求",
      "Option_B": "完全不動",
      "Option_C": "高強度プライオ",
      "Option_D": "体幹筋の耐久性強化",
      "Correct": "A",
      "Explanation": "体幹筋の耐久性と制御力を高めることが、腰部再発予防に効果的である。",
      "Tag_Cause": "体幹筋機能低下",
      "Tag_Process": "耐久性強化|制御訓練",
      "Tag_Outcome": "再発抑制|腰部安定化"
    },
    {
      "Title": "NSCA CSCS 問題集 (61/90)",
      "Date": "2025年11月25日",
      "Field": "リハビリテーションと再調整",
      "Theme": "動作再学習",
      "Level": "Level 4",
      "QuizType": "",
      "Number": 21,
      "Question": "ACL​再建後のジャンプ系導入で優先すべき指導要素はどれか？",
      "Option_A": "着地メカニクスと膝内反抑制",
      "Option_B": "ジャンプ高のみ追求",
      "Option_C": "休息なし反復",
      "Option_D": "痛み無視で強行",
      "Correct": "A",
      "Explanation": "まず着地制御と股関節戦略を確立し，膝内反を抑制してから強度を段階的に上げる。",
      "Tag_Cause": "膝内反|股関節制御不足",
      "Tag_Process": "着地制御|股関節戦略習得",
      "Tag_Outcome": "動作安定|再受傷防止"
    },
    {
      "Title": "NSCA CSCS 問題集 (61/90)",
      "Date": "2025年11月25日",
      "Field": "リハビリテーションと再調整",
      "Theme": "復帰基準",
      "Level": "Level 4",
      "QuizType": "",
      "Number": 22,
      "Question": "競技復帰判断で必要な基準はどれか？",
      "Option_A": "疼痛の持続",
      "Option_B": "腫脹の増悪",
      "Option_C": "患側筋力が健側の90％以上",
      "Option_D": "ROM制限残存",
      "Correct": "A",
      "Explanation": "左右差10％以内を目標とする筋力回復が一般的基準。疼痛や腫脹増悪時は復帰延期が妥当。",
      "Tag_Cause": "筋力左右差評価",
      "Tag_Process": "疼痛|腫脹管理",
      "Tag_Outcome": "復帰判断|再発防止"
    },
    {
      "Title": "NSCA CSCS 問題集 (61/90)",
      "Date": "2025年11月25日",
      "Field": "リハビリテーションと再調整",
      "Theme": "復帰基準",
      "Level": "Level 4",
      "QuizType": "",
      "Number": 23,
      "Question": "肩関節リハで反復上肢作業能力を確認するテストはどれか？",
      "Option_A": "Yバランステスト",
      "Option_B": "CKCUEST",
      "Option_C": "シャトルラン",
      "Option_D": "Borgスケール",
      "Correct": "A",
      "Explanation": "CKCUESTは上肢の持久性・安定性を評価するテストで，復帰判断に有用。",
      "Tag_Cause": "上肢安定性評価",
      "Tag_Process": "CKCUEST実施",
      "Tag_Outcome": "復帰基準設定|持久力評価"
    },
    {
      "Title": "NSCA CSCS 問題集 (61/90)",
      "Date": "2025年11月25日",
      "Field": "リハビリテーションと再調整",
      "Theme": "統合的再調整",
      "Level": "Level 4",
      "QuizType": "",
      "Number": 24,
      "Question": "筋力からパワー移行期に適切な負荷設定はどれか？",
      "Option_A": "常に最大負荷のみ",
      "Option_B": "可動域を狭める",
      "Option_C": "痛み無視で加速",
      "Option_D": "軽中負荷で速度意図を維持",
      "Correct": "A",
      "Explanation": "中程度負荷で速度を意識して動作することでパワー発揮を最適化できる。",
      "Tag_Cause": "中負荷設定",
      "Tag_Process": "速度意識動作",
      "Tag_Outcome": "パワー発揮最適化|機能移行"
    },
    {
      "Title": "NSCA CSCS 問題集 (61/90)",
      "Date": "2025年11月25日",
      "Field": "リハビリテーションと再調整",
      "Theme": "段階的復帰設計",
      "Level": "Level 4",
      "QuizType": "",
      "Number": 25,
      "Question": "復帰段階のサーキットで重視すべき変数はどれか？",
      "Option_A": "最大重量",
      "Option_B": "反復無制限",
      "Option_C": "休息時間と動作品質",
      "Option_D": "疼痛増悪",
      "Correct": "A",
      "Explanation": "回復期のサーキットでは心肺・筋持久向上を図りつつ，休息管理とフォーム維持を優先する。",
      "Tag_Cause": "回復期設計",
      "Tag_Process": "休息管理|フォーム維持",
      "Tag_Outcome": "持久力向上|安全復帰"
    },
    {
      "Title": "NSCA CSCS 問題集 (61/90)",
      "Date": "2025年11月25日",
      "Field": "リハビリテーションと再調整",
      "Theme": "再受傷予防",
      "Level": "Level 5",
      "QuizType": "",
      "Number": 26,
      "Question": "再受傷予防プログラムの構成で最も包括的なのはどれか？",
      "Option_A": "筋力のみ特化",
      "Option_B": "可動性・安定性・着地制御の統合",
      "Option_C": "柔軟性のみ強調",
      "Option_D": "有酸素のみ実施",
      "Correct": "A",
      "Explanation": "複数要素を統合的に扱うことで再受傷リスクを低減する。Field整合良好。",
      "Tag_Cause": "多要素統合",
      "Tag_Process": "安定化筋強化|動作制御訓練",
      "Tag_Outcome": "再受傷率低減|機能改善"
    },
    {
      "Title": "NSCA CSCS 問題集 (61/90)",
      "Date": "2025年11月25日",
      "Field": "リハビリテーションと再調整",
      "Theme": "競技復帰",
      "Level": "Level 5",
      "QuizType": "",
      "Number": 27,
      "Question": "試合直前​2〜3​日前に行う“プライミング”の目的はどれか？",
      "Option_A": "最大筋損傷",
      "Option_B": "ボリューム負荷増",
      "Option_C": "完全休養固定",
      "Option_D": "神経活性維持と疲労残留回避",
      "Correct": "A",
      "Explanation": "軽中負荷・高速動作で神経を活性化し、疲労を残さず出力性を保つ。",
      "Tag_Cause": "神経活性刺激",
      "Tag_Process": "軽中負荷高速動作",
      "Tag_Outcome": "出力維持|疲労抑制"
    },
    {
      "Title": "NSCA CSCS 問題集 (61/90)",
      "Date": "2025年11月25日",
      "Field": "リハビリテーションと再調整",
      "Theme": "段階的復帰設計",
      "Level": "Level 5",
      "QuizType": "",
      "Number": 28,
      "Question": "チーム競技での段階的復帰順序として妥当なのはどれか？",
      "Option_A": "個別→制限練習→全面→出場",
      "Option_B": "出場→個別→全面",
      "Option_C": "全面→制限→出場",
      "Option_D": "制限→出場→個別",
      "Correct": "A",
      "Explanation": "個別練習から始め、負荷反応を観察しながら制限付き→全面練習→試合へ進行する。",
      "Tag_Cause": "個別練習開始",
      "Tag_Process": "負荷反応評価|練習段階進行",
      "Tag_Outcome": "安全出場|競技復帰"
    },
    {
      "Title": "NSCA CSCS 問題集 (61/90)",
      "Date": "2025年11月25日",
      "Field": "リハビリテーションと再調整",
      "Theme": "競技復帰",
      "Level": "Level 5",
      "QuizType": "",
      "Number": 29,
      "Question": "復帰直後の出場時間管理の基本方針として適切なのはどれか？",
      "Option_A": "初戦から制限なし",
      "Option_B": "段階的ミニッツ制限＋翌日反応で調整",
      "Option_C": "痛みが出ても固定制限で維持",
      "Option_D": "コーチ裁量のみで決定",
      "Correct": "A",
      "Explanation": "負荷反応（痛み・腫脹・主観疲労）を翌日に評価し、段階的に出場時間を延長する。過負荷を避け再受傷リスクを抑える。",
      "Tag_Cause": "負荷反応評価",
      "Tag_Process": "翌日疲労確認|時間管理",
      "Tag_Outcome": "段階的出場|再受傷防止"
    },
    {
      "Title": "NSCA CSCS 問題集 (61/90)",
      "Date": "2025年11月25日",
      "Field": "リハビリテーションと再調整",
      "Theme": "再受傷予防",
      "Level": "Level 5",
      "QuizType": "",
      "Number": 30,
      "Question": "シーズン中の再受傷予防を組織として運用する際​、​最も重要な仕組みはどれか？",
      "Option_A": "医療・S&C・コーチで共有プロトコルと週次レビュー",
      "Option_B": "個人任せの自主判断",
      "Option_C": "SNSでの自己申告",
      "Option_D": "試合前のみチェック",
      "Correct": "A",
      "Explanation": "多職種間で評価指標と介入手順を共有し、週次でKPIと症状をレビューする体制が遵守率と介入の一貫性を高める。",
      "Tag_Cause": "評価基準共有|介入手順統一",
      "Tag_Process": "週次レビュー|遵守率向上",
      "Tag_Outcome": "組織的再発防止"
    }
  ]
}