{
  "day": "20251220",
  "total": 30,
  "questions": [
    {
      "Title": "NSCA CSCS 問題集 (86/90)",
      "Date": "2025年12月20日",
      "Field": "プログラムデザイン",
      "Theme": "トレーニング原則",
      "Level": "Level 1",
      "QuizType": "",
      "Number": 1,
      "Question": "初心者の多関節種目で週当たりの基本頻度として妥当なのはどれか？",
      "Option_A": "週2–3回/全身",
      "Option_B": "週1回/全身のみ",
      "Option_C": "週6回/同部位連日",
      "Option_D": "月1回/全身",
      "Correct": "A",
      "Explanation": "技術学習と回復を両立する一般的頻度。",
      "Tag_Cause": "初心者適応",
      "Tag_Process": "技術学習|回復確保",
      "Tag_Outcome": "頻度最適化"
    },
    {
      "Title": "NSCA CSCS 問題集 (86/90)",
      "Date": "2025年12月20日",
      "Field": "プログラムデザイン",
      "Theme": "トレーニング原則",
      "Level": "Level 1",
      "QuizType": "",
      "Number": 2,
      "Question": "筋力向上初期のボリューム設計で無難なのはどれか？",
      "Option_A": "10セット以上から開始",
      "Option_B": "セットは0でよい",
      "Option_C": "毎回限界まで多数セット",
      "Option_D": "1種目1–3セット",
      "Correct": "A",
      "Explanation": "低〜中ボリュームで漸進が安全。",
      "Tag_Cause": "初期負荷設定",
      "Tag_Process": "漸進的ボリューム増加",
      "Tag_Outcome": "安全な筋力向上"
    },
    {
      "Title": "NSCA CSCS 問題集 (86/90)",
      "Date": "2025年12月20日",
      "Field": "プログラムデザイン",
      "Theme": "トレーニング原則",
      "Level": "Level 1",
      "QuizType": "",
      "Number": 3,
      "Question": "初学者のエクササイズ順序で推奨されるのはどれか？",
      "Option_A": "孤立→小筋群→大筋群",
      "Option_B": "大筋群→小筋群→孤立",
      "Option_C": "好きな順",
      "Option_D": "疲労時に複合種目",
      "Correct": "A",
      "Explanation": "複合/大筋群を先行で品質と安全を確保。",
      "Tag_Cause": "複合運動優先",
      "Tag_Process": "大筋群先行配置",
      "Tag_Outcome": "動作品質確保"
    },
    {
      "Title": "NSCA CSCS 問題集 (86/90)",
      "Date": "2025年12月20日",
      "Field": "プログラムデザイン",
      "Theme": "筋肥大期と神経系期",
      "Level": "Level 1",
      "QuizType": "",
      "Number": 4,
      "Question": "筋肥大狙いの目安反復域として一般的なのはどれか？",
      "Option_A": "1–3回",
      "Option_B": "20–30回固定",
      "Option_C": "6–12回",
      "Option_D": "常に50回以上",
      "Correct": "A",
      "Explanation": "中レップ域は機械的張力と代謝刺激の両立。",
      "Tag_Cause": "中レップ域設定",
      "Tag_Process": "張力|代謝刺激両立",
      "Tag_Outcome": "筋肥大促進"
    },
    {
      "Title": "NSCA CSCS 問題集 (86/90)",
      "Date": "2025年12月20日",
      "Field": "プログラムデザイン",
      "Theme": "トレーニング原則",
      "Level": "Level 1",
      "QuizType": "",
      "Number": 5,
      "Question": "初期の休息時間設定で筋力目的に近いのはどれか？",
      "Option_A": "30秒以内",
      "Option_B": "60–90秒",
      "Option_C": "2–5分",
      "Option_D": "休息なし",
      "Correct": "A",
      "Explanation": "高強度挙上には十分なATP-PC回復が要る。",
      "Tag_Cause": "高強度挙上",
      "Tag_Process": "ATP-PC回復確保",
      "Tag_Outcome": "最大筋力発揮"
    },
    {
      "Title": "NSCA CSCS 問題集 (86/90)",
      "Date": "2025年12月20日",
      "Field": "プログラムデザイン",
      "Theme": "漸進的過負荷",
      "Level": "Level 1",
      "QuizType": "",
      "Number": 6,
      "Question": "漸進性過負荷の基本手段として妥当なのはどれか？",
      "Option_A": "重量・レップ・セットの計画的増加",
      "Option_B": "常に気分で変える",
      "Option_C": "休息時間のみ増やす",
      "Option_D": "フォーム無視で重量急増",
      "Correct": "A",
      "Explanation": "負荷・量・密度の計画的漸増が原則。",
      "Tag_Cause": "負荷増加計画",
      "Tag_Process": "量|密度調整",
      "Tag_Outcome": "漸進的過負荷達成"
    },
    {
      "Title": "NSCA CSCS 問題集 (86/90)",
      "Date": "2025年12月20日",
      "Field": "プログラムデザイン",
      "Theme": "トレーニング原則",
      "Level": "Level 1",
      "QuizType": "",
      "Number": 7,
      "Question": "一般的な全身プログラムの週内配置として妥当なのはどれか？",
      "Option_A": "連日同一刺激を反復",
      "Option_B": "週1回のみ",
      "Option_C": "7日連続",
      "Option_D": "月水金の非連日",
      "Correct": "A",
      "Explanation": "非連日配置で回復と学習を確保しやすい。",
      "Tag_Cause": "全身配置計画",
      "Tag_Process": "非連日スケジュール化",
      "Tag_Outcome": "学習|回復両立"
    },
    {
      "Title": "NSCA CSCS 問題集 (86/90)",
      "Date": "2025年12月20日",
      "Field": "プログラムデザイン",
      "Theme": "スピード系",
      "Level": "Level 1",
      "QuizType": "",
      "Number": 8,
      "Question": "パワー種目の実施タイミングとして適切なのはどれか？",
      "Option_A": "疲労後半に配置",
      "Option_B": "セッション冒頭のフレッシュ時",
      "Option_C": "有酸素後の最後",
      "Option_D": "いつでも同じ",
      "Correct": "A",
      "Explanation": "高速度/高出力は疲労前に行うのが定石。",
      "Tag_Cause": "高速度要求",
      "Tag_Process": "疲労前実施",
      "Tag_Outcome": "最大出力維持"
    },
    {
      "Title": "NSCA CSCS 問題集 (86/90)",
      "Date": "2025年12月20日",
      "Field": "プログラムデザイン",
      "Theme": "トレーニング原則",
      "Level": "Level 1",
      "QuizType": "",
      "Number": 9,
      "Question": "初心者の主観的強度管理で適切なのはどれか？",
      "Option_A": "RPE/RIRを用いる",
      "Option_B": "勘に任せる",
      "Option_C": "常に限界まで",
      "Option_D": "毎回最大重量",
      "Correct": "A",
      "Explanation": "主観指標を導入し安全に自己調整する。",
      "Tag_Cause": "主観指標導入",
      "Tag_Process": "RPE|RIR活用",
      "Tag_Outcome": "安全な強度管理"
    },
    {
      "Title": "NSCA CSCS 問題集 (86/90)",
      "Date": "2025年12月20日",
      "Field": "プログラムデザイン",
      "Theme": "トレーニング原則",
      "Level": "Level 1",
      "QuizType": "",
      "Number": 10,
      "Question": "ウォームアップの特異性原則として正しいのはどれか？",
      "Option_A": "静的長時間のみ",
      "Option_B": "上肢のみ",
      "Option_C": "本番動作に近いドリルを含める",
      "Option_D": "呼吸停止を推奨",
      "Correct": "A",
      "Explanation": "特異的動作で神経/可動域を整える。",
      "Tag_Cause": "競技動作分析",
      "Tag_Process": "特異的ウォームアップ実施",
      "Tag_Outcome": "神経活性化|可動域向上"
    },
    {
      "Title": "NSCA CSCS 問題集 (86/90)",
      "Date": "2025年12月20日",
      "Field": "プログラムデザイン",
      "Theme": "トレーニング原則",
      "Level": "Level 2",
      "QuizType": "",
      "Number": 11,
      "Question": "筋力向上の強度目安で多関節主運動の典型はどれか？",
      "Option_A": "30–50%1RM",
      "Option_B": "70–85%1RM",
      "Option_C": "50–60%1RM",
      "Option_D": ">95%1RMのみ",
      "Correct": "A",
      "Explanation": "70–85%1RM域は筋力発達の中心的レンジ。",
      "Tag_Cause": "多関節運動選定",
      "Tag_Process": "中高強度負荷設定",
      "Tag_Outcome": "筋力発達促進"
    },
    {
      "Title": "NSCA CSCS 問題集 (86/90)",
      "Date": "2025年12月20日",
      "Field": "プログラムデザイン",
      "Theme": "トレーニング原則",
      "Level": "Level 2",
      "QuizType": "",
      "Number": 12,
      "Question": "上肢​/​下肢の交互サーキットで狙える効果はどれか？",
      "Option_A": "同部位の局所疲労蓄積",
      "Option_B": "出力は常に低下",
      "Option_C": "怪我リスクのみ増大",
      "Option_D": "全身密度↑で心肺負荷も付与",
      "Correct": "A",
      "Explanation": "非競合配置で休息短縮と密度向上を両立。",
      "Tag_Cause": "部位交互配置",
      "Tag_Process": "非競合休息利用",
      "Tag_Outcome": "密度向上|疲労抑制"
    },
    {
      "Title": "NSCA CSCS 問題集 (86/90)",
      "Date": "2025年12月20日",
      "Field": "プログラムデザイン",
      "Theme": "トレーニング原則",
      "Level": "Level 2",
      "QuizType": "",
      "Number": 13,
      "Question": "VBT​設計で速度低下率​（​​%​VL​）​を用いる主目的はどれか？",
      "Option_A": "常に失敗まで実施",
      "Option_B": "重量記録のみ重視",
      "Option_C": "速度表示は無視",
      "Option_D": "疲労を制御し質を一定化",
      "Correct": "A",
      "Explanation": "%VLでセット打ち切りを管理し狙いを維持。",
      "Tag_Cause": "速度指標測定",
      "Tag_Process": "%VL閾値設定",
      "Tag_Outcome": "品質維持|疲労制御"
    },
    {
      "Title": "NSCA CSCS 問題集 (86/90)",
      "Date": "2025年12月20日",
      "Field": "プログラムデザイン",
      "Theme": "混成模擬セット",
      "Level": "Level 2",
      "QuizType": "",
      "Number": 14,
      "Question": "アンチゴニスト​・​ペア法​（​A1​/​A2​）​の利点はどれか？",
      "Option_A": "神経効率と時間効率の向上",
      "Option_B": "休息が極端に延びる",
      "Option_C": "片側のみ疲労増",
      "Option_D": "負荷設定不能",
      "Correct": "A",
      "Explanation": "拮抗筋交互で時間短縮と動作質の維持に寄与。",
      "Tag_Cause": "拮抗筋配置",
      "Tag_Process": "交互動作実施",
      "Tag_Outcome": "時間短縮|動作効率化"
    },
    {
      "Title": "NSCA CSCS 問題集 (86/90)",
      "Date": "2025年12月20日",
      "Field": "プログラムデザイン",
      "Theme": "トレーニング原則",
      "Level": "Level 2",
      "QuizType": "",
      "Number": 15,
      "Question": "週当たりボリューム​（​セット数​）​で筋肥大の一般的範囲はどれか？",
      "Option_A": "各部位1–3/週",
      "Option_B": "各部位40–60/週",
      "Option_C": "各部位10–20/週",
      "Option_D": "ゼロが最適",
      "Correct": "A",
      "Explanation": "多くのレビューで10–20セット/週が目安。",
      "Tag_Cause": "週当たりセット設定",
      "Tag_Process": "中ボリューム設計",
      "Tag_Outcome": "筋肥大最適化"
    },
    {
      "Title": "NSCA CSCS 問題集 (86/90)",
      "Date": "2025年12月20日",
      "Field": "プログラムデザイン",
      "Theme": "混成模擬セット",
      "Level": "Level 3",
      "QuizType": "",
      "Number": 16,
      "Question": "クラスターセットの主な利点として適切なのはどれか？",
      "Option_A": "常に疲労を最大化してボリュームを増やす",
      "Option_B": "セット内に短休息を挟み平均挙上速度・出力を維持",
      "Option_C": "有酸素能力のみを高める",
      "Option_D": "負荷を極端に下げてフォームを無視",
      "Correct": "A",
      "Explanation": "短休息で部分回復を挟み各反復の力・速度を保つ。パワー/筋力狙いで高品質レップを積める。",
      "Tag_Cause": "短休息分割",
      "Tag_Process": "部分回復挿入",
      "Tag_Outcome": "出力維持|高品質反復"
    },
    {
      "Title": "NSCA CSCS 問題集 (86/90)",
      "Date": "2025年12月20日",
      "Field": "プログラムデザイン",
      "Theme": "期分け理論",
      "Level": "Level 3",
      "QuizType": "",
      "Number": 17,
      "Question": "日内​（​デイリ​）​非線形モデルの利点はどれか？",
      "Option_A": "単調な適応のみ",
      "Option_B": "回復を常に阻害",
      "Option_C": "頻繁な刺激変化で停滞回避",
      "Option_D": "進捗が測れない",
      "Correct": "A",
      "Explanation": "高・中・軽日を巡回し適応と回復を両立。",
      "Tag_Cause": "日内負荷変動",
      "Tag_Process": "高中軽日巡回",
      "Tag_Outcome": "適応|回復両立"
    },
    {
      "Title": "NSCA CSCS 問題集 (86/90)",
      "Date": "2025年12月20日",
      "Field": "プログラムデザイン",
      "Theme": "スピード系",
      "Level": "Level 3",
      "QuizType": "",
      "Number": 18,
      "Question": "パワー向上でバー速度を優先するときの目安はどれか？",
      "Option_A": "RIR2–4で高速意図",
      "Option_B": "RIR0固定",
      "Option_C": "常にスローテンポ",
      "Option_D": "エキセントリックは停止",
      "Correct": "A",
      "Explanation": "余裕反復を残し速度重視で出力を伸ばす。",
      "Tag_Cause": "バー速度重視",
      "Tag_Process": "余裕反復確保",
      "Tag_Outcome": "出力最大化"
    },
    {
      "Title": "NSCA CSCS 問題集 (86/90)",
      "Date": "2025年12月20日",
      "Field": "プログラムデザイン",
      "Theme": "競技別デザイン",
      "Level": "Level 3",
      "QuizType": "",
      "Number": 19,
      "Question": "競技特異性の原則に沿った下肢プログラムの例はどれか？",
      "Option_A": "上肢孤立のみ",
      "Option_B": "静的収縮中心",
      "Option_C": "不安定面のみ多用",
      "Option_D": "水平/垂直方向の力発揮を再現",
      "Correct": "A",
      "Explanation": "方向・速度・可動域の類似性が転移を高める。",
      "Tag_Cause": "競技動作分析",
      "Tag_Process": "方向|速度一致設計",
      "Tag_Outcome": "転移効果向上"
    },
    {
      "Title": "NSCA CSCS 問題集 (86/90)",
      "Date": "2025年12月20日",
      "Field": "プログラムデザイン",
      "Theme": "テーパー",
      "Level": "Level 3",
      "QuizType": "",
      "Number": 20,
      "Question": "デロード週の代表的設定はどれか？",
      "Option_A": "強度・容量とも増加",
      "Option_B": "容量30–50%減、強度は適度に維持",
      "Option_C": "全停止のみ",
      "Option_D": "新規高難度を大量導入",
      "Correct": "A",
      "Explanation": "容量を主に落として回復、神経的質は保つ。",
      "Tag_Cause": "負荷調整実施",
      "Tag_Process": "容量低減|質維持",
      "Tag_Outcome": "回復促進|神経活性維持"
    },
    {
      "Title": "NSCA CSCS 問題集 (86/90)",
      "Date": "2025年12月20日",
      "Field": "プログラムデザイン",
      "Theme": "テーパー",
      "Level": "Level 3",
      "QuizType": "",
      "Number": 21,
      "Question": "テスト期​（​1RM​/​スプリント等​）​前週の調整として妥当なのはどれか？",
      "Option_A": "ボリューム減・強度は維持〜やや高め",
      "Option_B": "ボリューム増・強度減なし",
      "Option_C": "すべて中止",
      "Option_D": "無計画",
      "Correct": "A",
      "Explanation": "疲労を抜きつつ神経駆動を保つ短期テーパー。",
      "Tag_Cause": "試験前調整",
      "Tag_Process": "短期テーパー適用",
      "Tag_Outcome": "疲労除去|神経駆動維持"
    },
    {
      "Title": "NSCA CSCS 問題集 (86/90)",
      "Date": "2025年12月20日",
      "Field": "プログラムデザイン",
      "Theme": "期分け理論",
      "Level": "Level 4",
      "QuizType": "",
      "Number": 22,
      "Question": "同時トレの干渉低減で有効なのはどれか？",
      "Option_A": "持久直後に最大下肢筋力",
      "Option_B": "常に同日に密集",
      "Option_C": "時間分離や順序工夫・量管理",
      "Option_D": "高ボリューム持久を先行固定",
      "Correct": "A",
      "Explanation": "順序と間隔・総量調整でシグナル干渉を抑える。",
      "Tag_Cause": "同時刺激発生",
      "Tag_Process": "順序|間隔管理",
      "Tag_Outcome": "シグナル干渉抑制"
    },
    {
      "Title": "NSCA CSCS 問題集 (86/90)",
      "Date": "2025年12月20日",
      "Field": "プログラムデザイン",
      "Theme": "スピード系",
      "Level": "Level 4",
      "QuizType": "",
      "Number": 23,
      "Question": "スピード–ストレングス領域の負荷目安はどれか？",
      "Option_A": "~30%1RM",
      "Option_B": "~90–100%1RM",
      "Option_C": "自体重のみ",
      "Option_D": "~50–70%1RM",
      "Correct": "A",
      "Explanation": "中負荷×高速度域で速度–力の中間を狙う。",
      "Tag_Cause": "中負荷設定",
      "Tag_Process": "高速度挙上",
      "Tag_Outcome": "速度–力最適領域刺激"
    },
    {
      "Title": "NSCA CSCS 問題集 (86/90)",
      "Date": "2025年12月20日",
      "Field": "プログラムデザイン",
      "Theme": "スプリット方式",
      "Level": "Level 4",
      "QuizType": "",
      "Number": 24,
      "Question": "上級者の週分割で“押​/​引​/​脚”を採る利点はどれか？",
      "Option_A": "同部位を連日疲労",
      "Option_B": "常に出力低下",
      "Option_C": "回復窓を確保しつつボリューム配分",
      "Option_D": "競技練習と競合増",
      "Correct": "A",
      "Explanation": "非競合群で分割し回復と量の最適化がしやすい。",
      "Tag_Cause": "部位分割計画",
      "Tag_Process": "押引脚分離",
      "Tag_Outcome": "回復|総量最適化"
    },
    {
      "Title": "NSCA CSCS 問題集 (86/90)",
      "Date": "2025年12月20日",
      "Field": "プログラムデザイン",
      "Theme": "トレーニング原則（リハビリテーション）",
      "Level": "Level 4",
      "QuizType": "",
      "Number": 25,
      "Question": "リターン​・​トゥ​・​プレー初期ブロックの優先はどれか？",
      "Option_A": "最大強度の早期復帰",
      "Option_B": "痛み/腫脹ゼロ基準と段階的負荷",
      "Option_C": "新規高難度を多用",
      "Option_D": "競技特異動作のみ",
      "Correct": "A",
      "Explanation": "症状基準と段階進行で安全な復帰を設計。",
      "Tag_Cause": "復帰初期設計",
      "Tag_Process": "症状基準|段階進行",
      "Tag_Outcome": "安全な競技復帰"
    },
    {
      "Title": "NSCA CSCS 問題集 (86/90)",
      "Date": "2025年12月20日",
      "Field": "プログラムデザイン",
      "Theme": "トレーニング原則（特殊集団の考慮）",
      "Level": "Level 4",
      "QuizType": "",
      "Number": 26,
      "Question": "高齢者プログラム設計でまず重視するのはどれか？",
      "Option_A": "不安定面の多用",
      "Option_B": "最大速度のみ追求",
      "Option_C": "休息を極端に短縮",
      "Option_D": "支持性と可動要求の適正化",
      "Correct": "A",
      "Explanation": "安定支持と適正ROMで安全性と自立性を確保。",
      "Tag_Cause": "高齢者特性考慮",
      "Tag_Process": "安定支持|ROM調整",
      "Tag_Outcome": "安全性|自立性確保"
    },
    {
      "Title": "NSCA CSCS 問題集 (86/90)",
      "Date": "2025年12月20日",
      "Field": "プログラムデザイン",
      "Theme": "期分け理論",
      "Level": "Level 5",
      "QuizType": "",
      "Number": 27,
      "Question": "ブロックピリオド化で“アキュメレーション”の主眼はどれか？",
      "Option_A": "ピーキングの直前出力最大化",
      "Option_B": "一般的作業能力と技術基盤の積上げ",
      "Option_C": "完全休止",
      "Option_D": "競技特異のみ",
      "Correct": "A",
      "Explanation": "基盤体力・技術の蓄積期で後続フェーズを支える。",
      "Tag_Cause": "基盤期設計",
      "Tag_Process": "体力|技術蓄積",
      "Tag_Outcome": "後続フェーズ支援"
    },
    {
      "Title": "NSCA CSCS 問題集 (86/90)",
      "Date": "2025年12月20日",
      "Field": "プログラムデザイン",
      "Theme": "トレーニング原則",
      "Level": "Level 5",
      "QuizType": "",
      "Number": 28,
      "Question": "オートレギュレーションで​RIR​を使う利点はどれか？",
      "Option_A": "日内変動を無視",
      "Option_B": "常に失敗まで",
      "Option_C": "当日調子に応じ負荷/レップを微調整",
      "Option_D": "週次でのみ修正",
      "Correct": "A",
      "Explanation": "RIR基準で狙い強度を保ちつつ安全に調整。",
      "Tag_Cause": "RIR活用",
      "Tag_Process": "強度|反復調整",
      "Tag_Outcome": "安全な自己調整"
    },
    {
      "Title": "NSCA CSCS 問題集 (86/90)",
      "Date": "2025年12月20日",
      "Field": "プログラムデザイン",
      "Theme": "年間計画",
      "Level": "Level 5",
      "QuizType": "",
      "Number": 29,
      "Question": "年間計画で“メゾサイクル”に相当する期間はどれか？",
      "Option_A": "数週間〜数か月",
      "Option_B": "1–7日",
      "Option_C": "1年超",
      "Option_D": "数時間",
      "Correct": "A",
      "Explanation": "メゾは数週〜数か月の中期単位を指す。",
      "Tag_Cause": "年間構成策定",
      "Tag_Process": "中期単位設定",
      "Tag_Outcome": "周期的適応形成"
    },
    {
      "Title": "NSCA CSCS 問題集 (86/90)",
      "Date": "2025年12月20日",
      "Field": "プログラムデザイン",
      "Theme": "ピーキング",
      "Level": "Level 5",
      "QuizType": "",
      "Number": 30,
      "Question": "ピーキング期の特徴として妥当なのはどれか？",
      "Option_A": "長時間・高容量維持",
      "Option_B": "すべて中止",
      "Option_C": "新規刺激を大量導入",
      "Option_D": "容量を落とし神経的強度は維持",
      "Correct": "A",
      "Explanation": "疲労最小化しつつ最大出力を発揮できる準備。",
      "Tag_Cause": "負荷管理",
      "Tag_Process": "疲労除去|神経準備",
      "Tag_Outcome": "最大出力発揮"
    }
  ]
}